decima2/__init__.py
decima2/data/__init__.py
decima2/model/__init__.py
decima2/model/explanation/__init__.py
decima2/model/explanation/explanation_calculation.py
decima2/model/explanation/explanation_generation.py
decima2/outcome/__init__.py
decima2/outcome/nlp_explanations/__init__.py
decima2/outcome/nlp_explanations/explanation_generation.py
decima2/outcome/nlp_explanations/nlp_private_function.py
decima2/outcome/tabular_explanations/__init__.py
decima2/outcome/tabular_explanations/explanation_generation.py
decima2/utils/__init__.py
decima2/utils/data_utils.py
decima2/utils/model_utils.py
decima2/utils/nlp_utils.py
decima2/utils/utils.py
decima2/visualisation/__init__.py
decima2/visualisation/model/__init__.py
decima2/visualisation/model/visualisation_explanation.py
decima2/visualisation/outcome/__init__.py
decima2/visualisation/outcome/visualisation.py
decima2/visualisation/outcome/visualisation_nlp.py
decima2-0.4.2.dist-info/licenses/LICENSE
tests/__init__.py
tests/test_data_utils.py
tests/test_grouped_feature_importance.py
tests/test_individual_feature_importance.py
tests/test_individual_nlp_explanations.py
tests/test_model_feature_importance.py
tests/test_model_utils.py
decima2-0.4.2.dist-info/METADATA
decima2-0.4.2.dist-info/WHEEL
decima2-0.4.2.dist-info/top_level.txt
decima2-0.4.2.dist-info/RECORD
