Metadata-Version: 2.4
Name: decima2
Version: 0.4.2
Summary: Evaluation Toolkit for Machine Learning Models
Home-page: https://github.com/Decima2/Decima2Toolkit
Author: Torty Sivill
Author-email: torty.sivill@decima2.co.uk
Classifier: Programming Language :: Python :: 3
Classifier: License :: OSI Approved :: MIT License
Classifier: Operating System :: OS Independent
Requires-Python: >=3.7, <=3.12.7
License-File: LICENSE
Requires-Dist: dash<=2.18.1,>=2.14.0
Requires-Dist: numpy<=2.1.1
Requires-Dist: pandas<=2.2.3,>=1.3.0
Requires-Dist: plotly<=5.24.1,>=5.10.0
Requires-Dist: Requests<=2.32.3,>=2.20.0
Requires-Dist: scikit_learn<=1.5.2,>=1.0
Requires-Dist: setuptools>=58.0.4
Requires-Dist: shap<=0.46.0,>=0.4.0
Requires-Dist: torch<=2.4.0,>=1.13.0
Requires-Dist: keras<=3.8,>=2.4.0
Requires-Dist: tensorflow<=2.19.0,>2.10.0
Requires-Dist: pytest<=8.3.3,>=7.4.3
Requires-Dist: nltk<=3.9.1
Requires-Dist: sentence_transformers<5.0.0,>=2.2.0
Requires-Dist: tf-keras; python_version >= "3.9"
Dynamic: author
Dynamic: author-email
Dynamic: classifier
Dynamic: description
Dynamic: description-content-type
Dynamic: home-page
Dynamic: license-file
Dynamic: requires-dist
Dynamic: requires-python
Dynamic: summary
